calculadora/__init__.py
pedro_calculadora-0.1.0.dist-info/METADATA
pedro_calculadora-0.1.0.dist-info/WHEEL
pedro_calculadora-0.1.0.dist-info/top_level.txt
pedro_calculadora-0.1.0.dist-info/RECORD
