Metadata-Version: 2.4
Name: pedro-calculadora
Version: 0.1.0
Summary: Uma calculadora básica em python utilizada como introdução a publicação de libs no PyPi
Author-email: Pedro Ferreira <pedro@email.com>
License: MIT
Project-URL: Homepage, https://github.com/bedrohenr/calc-release
Project-URL: Documentation, https://github.com/bedrohenr/calc-release
Project-URL: Repository, https://github.com/bedrohenr/calc-release
Project-URL: Issues, https://github.com/bedrohenr/calc-release/issues
Classifier: Programming Language :: Python :: 3
Classifier: License :: OSI Approved :: MIT License
Classifier: Operating System :: OS Independent
Requires-Python: >=3.7
